README.md
pyproject.toml
setup.py
pyramid_https_session_core/__init__.py
pyramid_https_session_core.egg-info/PKG-INFO
pyramid_https_session_core.egg-info/SOURCES.txt
pyramid_https_session_core.egg-info/dependency_links.txt
pyramid_https_session_core.egg-info/not-zip-safe
pyramid_https_session_core.egg-info/requires.txt
pyramid_https_session_core.egg-info/top_level.txt